pywebframework_uz/__init__.py
pywebframework_uz/app.py
pywebframework_uz/middleware.py
pywebframework_uz/response.py
pywebframework_uz-0.1.4.dist-info/METADATA
pywebframework_uz-0.1.4.dist-info/WHEEL
pywebframework_uz-0.1.4.dist-info/top_level.txt
pywebframework_uz-0.1.4.dist-info/RECORD
